diskord/__init__.py
diskord/__main__.py
diskord/abc.py
diskord/activity.py
diskord/appinfo.py
diskord/application_commands.py
diskord/asset.py
diskord/audit_logs.py
diskord/backoff.py
diskord/channel.py
diskord/client.py
diskord/colour.py
diskord/components.py
diskord/context_managers.py
diskord/embeds.py
diskord/emoji.py
diskord/enums.py
diskord/errors.py
diskord/file.py
diskord/flags.py
diskord/gateway.py
diskord/guild.py
diskord/http.py
diskord/integrations.py
diskord/interactions.py
diskord/invite.py
diskord/iterators.py
diskord/member.py
diskord/mentions.py
diskord/message.py
diskord/mixins.py
diskord/object.py
diskord/oggparse.py
diskord/opus.py
diskord/partial_emoji.py
diskord/permissions.py
diskord/player.py
diskord/py.typed
diskord/raw_models.py
diskord/reaction.py
diskord/role.py
diskord/shard.py
diskord/stage_instance.py
diskord/state.py
diskord/sticker.py
diskord/team.py
diskord/template.py
diskord/threads.py
diskord/user.py
diskord/utils.py
diskord/voice_client.py
diskord/welcome_screen.py
diskord/widget.py
diskord/application/__init__.py
diskord/application/command.py
diskord/application/context_menus.py
diskord/application/mixins.py
diskord/application/permissions.py
diskord/application/slash.py
diskord/application/types.py
diskord/bin/libopus-0.x64.dll
diskord/bin/libopus-0.x86.dll
diskord/ext/commands/__init__.py
diskord/ext/commands/_types.py
diskord/ext/commands/bot.py
diskord/ext/commands/cog.py
diskord/ext/commands/context.py
diskord/ext/commands/converter.py
diskord/ext/commands/cooldowns.py
diskord/ext/commands/core.py
diskord/ext/commands/errors.py
diskord/ext/commands/flags.py
diskord/ext/commands/help.py
diskord/ext/commands/view.py
diskord/ext/tasks/__init__.py
diskord/types/__init__.py
diskord/types/activity.py
diskord/types/appinfo.py
diskord/types/audit_log.py
diskord/types/channel.py
diskord/types/components.py
diskord/types/embed.py
diskord/types/emoji.py
diskord/types/gateway.py
diskord/types/guild.py
diskord/types/integration.py
diskord-2.6.2.dist-info/LICENSE
diskord-2.6.2.dist-info/METADATA
diskord-2.6.2.dist-info/WHEEL
diskord-2.6.2.dist-info/top_level.txt
diskord-2.6.2.dist-info/RECORD
